{
  "minecraft:recipes/building_blocks/light_blue_wool": {
    "criteria": {
      "has_white_wool": "2021-04-06 17:44:57 +0500"
    },
    "done": true
  },
  "minecraft:recipes/food/cooked_mutton_from_campfire_cooking": {
    "criteria": {
      "has_mutton": "2021-04-06 17:44:57 +0500"
    },
    "done": true
  },
  "minecraft:recipes/decorations/grindstone": {
    "criteria": {
      "has_stone_slab": "2021-04-06 17:45:17 +0500"
    },
    "done": true
  },
  "minecraft:recipes/building_blocks/purple_wool": {
    "criteria": {
      "has_white_wool": "2021-04-06 17:44:57 +0500"
    },
    "done": true
  },
  "minecraft:recipes/tools/clock": {
    "criteria": {
      "has_redstone": "2021-04-06 17:43:29 +0500"
    },
    "done": true
  },
  "minecraft:recipes/building_blocks/lime_wool": {
    "criteria": {
      "has_white_wool": "2021-04-06 17:44:57 +0500"
    },
    "done": true
  },
  "minecraft:recipes/building_blocks/pink_wool": {
    "criteria": {
      "has_white_wool": "2021-04-06 17:44:57 +0500"
    },
    "done": true
  },
  "minecraft:recipes/tools/compass": {
    "criteria": {
      "has_redstone": "2021-04-06 17:43:29 +0500"
    },
    "done": true
  },
  "minecraft:recipes/building_blocks/gray_wool": {
    "criteria": {
      "has_white_wool": "2021-04-06 17:44:57 +0500"
    },
    "done": true
  },
  "minecraft:recipes/building_blocks/black_wool": {
    "criteria": {
      "has_white_wool": "2021-04-06 17:44:57 +0500"
    },
    "done": true
  },
  "minecraft:recipes/building_blocks/blue_wool": {
    "criteria": {
      "has_white_wool": "2021-04-06 17:44:57 +0500"
    },
    "done": true
  },
  "minecraft:recipes/redstone/redstone_block": {
    "criteria": {
      "has_redstone": "2021-04-06 17:43:29 +0500"
    },
    "done": true
  },
  "minecraft:recipes/decorations/white_bed": {
    "criteria": {
      "has_white_wool": "2021-04-06 17:44:57 +0500"
    },
    "done": true
  },
  "minecraft:recipes/building_blocks/green_wool": {
    "criteria": {
      "has_white_wool": "2021-04-06 17:44:57 +0500"
    },
    "done": true
  },
  "minecraft:recipes/redstone/piston": {
    "criteria": {
      "has_redstone": "2021-04-06 17:43:29 +0500"
    },
    "done": true
  },
  "minecraft:recipes/redstone/target": {
    "criteria": {
      "has_redstone": "2021-04-06 17:43:29 +0500"
    },
    "done": true
  },
  "minecraft:recipes/decorations/white_carpet": {
    "criteria": {
      "has_white_wool": "2021-04-06 17:44:57 +0500"
    },
    "done": true
  },
  "minecraft:recipes/building_blocks/brown_wool": {
    "criteria": {
      "has_white_wool": "2021-04-06 17:44:57 +0500"
    },
    "done": true
  },
  "minecraft:recipes/food/cooked_mutton_from_smoking": {
    "criteria": {
      "has_mutton": "2021-04-06 17:44:57 +0500"
    },
    "done": true
  },
  "minecraft:adventure/adventuring_time": {
    "criteria": {
      "minecraft:plains": "2021-04-06 17:43:29 +0500"
    },
    "done": false
  },
  "minecraft:recipes/building_blocks/magenta_wool": {
    "criteria": {
      "has_white_wool": "2021-04-06 17:44:57 +0500"
    },
    "done": true
  },
  "minecraft:recipes/building_blocks/orange_wool": {
    "criteria": {
      "has_white_wool": "2021-04-06 17:44:57 +0500"
    },
    "done": true
  },
  "minecraft:recipes/redstone/redstone_torch": {
    "criteria": {
      "has_redstone": "2021-04-06 17:43:29 +0500"
    },
    "done": true
  },
  "minecraft:recipes/redstone/note_block": {
    "criteria": {
      "has_redstone": "2021-04-06 17:43:29 +0500"
    },
    "done": true
  },
  "minecraft:recipes/decorations/painting": {
    "criteria": {
      "has_wool": "2021-04-06 17:44:57 +0500"
    },
    "done": true
  },
  "minecraft:recipes/building_blocks/light_gray_wool": {
    "criteria": {
      "has_white_wool": "2021-04-06 17:44:57 +0500"
    },
    "done": true
  },
  "minecraft:recipes/building_blocks/red_wool": {
    "criteria": {
      "has_white_wool": "2021-04-06 17:44:57 +0500"
    },
    "done": true
  },
  "minecraft:recipes/decorations/white_banner": {
    "criteria": {
      "has_white_wool": "2021-04-06 17:44:57 +0500"
    },
    "done": true
  },
  "minecraft:recipes/redstone/dropper": {
    "criteria": {
      "has_redstone": "2021-04-06 17:43:29 +0500"
    },
    "done": true
  },
  "minecraft:recipes/building_blocks/cyan_wool": {
    "criteria": {
      "has_white_wool": "2021-04-06 17:44:57 +0500"
    },
    "done": true
  },
  "minecraft:recipes/building_blocks/yellow_wool": {
    "criteria": {
      "has_white_wool": "2021-04-06 17:44:57 +0500"
    },
    "done": true
  },
  "minecraft:recipes/food/cooked_mutton": {
    "criteria": {
      "has_mutton": "2021-04-06 17:44:57 +0500"
    },
    "done": true
  },
  "minecraft:adventure/root": {
    "criteria": {
      "killed_something": "2021-04-06 17:44:56 +0500"
    },
    "done": true
  },
  "DataVersion": 2584
}